adafruit_tca9548a.py
adafruit_circuitpython_tca9548a-0.8.3.dist-info/licenses/LICENSE
adafruit_circuitpython_tca9548a-0.8.3.dist-info/METADATA
adafruit_circuitpython_tca9548a-0.8.3.dist-info/WHEEL
adafruit_circuitpython_tca9548a-0.8.3.dist-info/top_level.txt
adafruit_circuitpython_tca9548a-0.8.3.dist-info/RECORD
