Metadata-Version: 2.4
Name: adafruit-circuitpython-tca9548a
Version: 0.8.3
Summary: CircuitPython driver for the TCA9548A I2C Multiplexer.
Author-email: Adafruit Industries <circuitpython@adafruit.com>
License: MIT
Project-URL: Homepage, https://github.com/adafruit/Adafruit_CircuitPython_TCA9548A
Keywords: adafruit,tca9548a,i2c,multiplexer,hardware,micropython,circuitpython
Classifier: Intended Audience :: Developers
Classifier: Topic :: Software Development :: Libraries
Classifier: Topic :: Software Development :: Embedded Systems
Classifier: Topic :: System :: Hardware
Classifier: License :: OSI Approved :: MIT License
Classifier: Programming Language :: Python :: 3
License-File: LICENSE
Requires-Dist: Adafruit-Blinka
Requires-Dist: adafruit-circuitpython-busdevice
Requires-Dist: adafruit-circuitpython-typing
Requires-Dist: typing-extensions~=4.0
Provides-Extra: optional
Dynamic: license-file
